ytr.py
ytr-0.0.1.dist-info/entry_points.txt
ytr-0.0.1.dist-info/WHEEL
ytr-0.0.1.dist-info/METADATA
ytr-0.0.1.dist-info/RECORD
