Metadata-Version: 2.1
Name: ytr
Version: 0.0.1
Summary: Yandex.Translate prompt
Home-page: https://github.com/vrslev/ytr
License: MIT
Keywords: cli,yandex,translate,yandex-translate,translate-api
Author: Lev Vereshchagin
Author-email: mail@vrslev.com
Requires-Python: >=3.10,<3.11
Classifier: Development Status :: 3 - Alpha
Classifier: License :: OSI Approved :: MIT License
Classifier: Natural Language :: English
Classifier: Natural Language :: Russian
Classifier: Programming Language :: Python :: 3
Classifier: Programming Language :: Python :: 3.10
Classifier: Programming Language :: Python :: Implementation :: CPython
Classifier: Typing :: Typed
Requires-Dist: httpx (==0.22.0)
Requires-Dist: rich (==12.3.0)
Requires-Dist: typer (==0.4.1)
Project-URL: Repository, https://github.com/vrslev/ytr
